odoo/addons/stock_move_line_reserved_quant/README.rst
odoo/addons/stock_move_line_reserved_quant/__init__.py
odoo/addons/stock_move_line_reserved_quant/__manifest__.py
odoo/addons/stock_move_line_reserved_quant/i18n/de.po
odoo/addons/stock_move_line_reserved_quant/i18n/es.po
odoo/addons/stock_move_line_reserved_quant/i18n/it.po
odoo/addons/stock_move_line_reserved_quant/i18n/stock_move_line_reserved_quant.pot
odoo/addons/stock_move_line_reserved_quant/models/__init__.py
odoo/addons/stock_move_line_reserved_quant/models/stock_move.py
odoo/addons/stock_move_line_reserved_quant/models/stock_move_line.py
odoo/addons/stock_move_line_reserved_quant/readme/CONTRIBUTORS.rst
odoo/addons/stock_move_line_reserved_quant/readme/DESCRIPTION.rst
odoo/addons/stock_move_line_reserved_quant/static/description/icon.png
odoo/addons/stock_move_line_reserved_quant/static/description/index.html
odoo/addons/stock_move_line_reserved_quant/tests/__init__.py
odoo/addons/stock_move_line_reserved_quant/tests/test_reserved_quant.py
odoo/addons/stock_move_line_reserved_quant/views/stock_move_line.xml
odoo_addon_stock_move_line_reserved_quant-16.0.1.0.0.10.dist-info/METADATA
odoo_addon_stock_move_line_reserved_quant-16.0.1.0.0.10.dist-info/WHEEL
odoo_addon_stock_move_line_reserved_quant-16.0.1.0.0.10.dist-info/top_level.txt
odoo_addon_stock_move_line_reserved_quant-16.0.1.0.0.10.dist-info/RECORD
